metricspace-1.2.0.dist-info/METADATA
metricspace-1.2.0.dist-info/WHEEL
metricspace-1.2.0.dist-info/license_files/LICENSE
metricspace/model/calculate_spkd/spkd_functions.py
metricspace/model/calculate_spkd/__init__.py
metricspace/model/distclust.py
metricspace/model/__init__.py
metricspace/model/spkd.py
metricspace/metricspace_rs.pyi
metricspace/entropy/histjabi.py
metricspace/entropy/histinfo.py
metricspace/entropy/histbi.py
metricspace/entropy/histtpbi.py
metricspace/entropy/__init__.py
metricspace/entropy/tblxinfo.py
metricspace/entropy/tblxtpbi.py
metricspace/entropy/tblxbi.py
metricspace/__init__.py
metricspace/py.typed
metricspace/metricspace_rs.abi3.so
metricspace-1.2.0.dist-info/RECORD
