Metadata-Version: 2.1
Name: metricspace
Version: 1.2.0
Classifier: License :: OSI Approved :: MIT License
Classifier: Development Status :: 5 - Production/Stable
Classifier: Intended Audience :: Developers
Classifier: Intended Audience :: Science/Research
Classifier: Operating System :: OS Independent
Classifier: Programming Language :: Rust
Classifier: Programming Language :: Python :: Implementation :: CPython
Classifier: Programming Language :: Python :: Implementation :: PyPy
Classifier: Programming Language :: Python
Classifier: Programming Language :: Python :: 3
Requires-Dist: setuptools >=40.8.0
Requires-Dist: wheel
Requires-Dist: numba >=0.57.0
Requires-Dist: numpy >=1.24.3
License-File: LICENSE
Summary: A python translation of code originally theorized in: Metric-space analysis of spike trains: theory, algorithms, and application Jonathan D. Victor and Keith Purpura Network 8, 127-164 (1997)
Author-email: Flynn OConnell <flynnoconnell@gmail.com>, Jonathan D Victor <jdvicto@med.cornell.edu>
Requires-Python: >=3.7
Project-URL: homepage, https://github.com/NeuroPyPy/metricspace
Project-URL: repository, https://github.com/NeuroPyPy/metricspace
Project-URL: documentation, http://www-users.med.cornell.edu/~jdvicto/metricdf.html#algorithm
